timetable/cli.py
timetable/init.py
gbu_timetable-0.1.2.dist-info/METADATA
gbu_timetable-0.1.2.dist-info/WHEEL
gbu_timetable-0.1.2.dist-info/entry_points.txt
gbu_timetable-0.1.2.dist-info/top_level.txt
gbu_timetable-0.1.2.dist-info/RECORD
