Metadata-Version: 2.4
Name: gbu-timetable
Version: 0.1.2
Summary: Terminal-based timetable viewer for Gautam Buddha University
Author: Shashank Shekhar
License: MIT
Requires-Python: >=3.8
Requires-Dist: requests
Requires-Dist: readchar
Requires-Dist: rich
